neurometa/__init__.py
neurometa/common.py
neurometa/data_scrape/__init__.py
neurometa/data_scrape/main.py
neurometa/data_scrape/wikipedia_table.ods
neurometa/fly.py
neurometa/human.py
neurometa/model_animal.py
neurometa-2.0.0.dist-info/METADATA
neurometa-2.0.0.dist-info/WHEEL
neurometa-2.0.0.dist-info/RECORD
