Metadata-Version: 2.1
Name: neurometa
Version: 2.0.0
Summary: Package for generating metadata related to neuroscience
Home-page: https://github.com/memorycircuits/neurometa
License: BSD-3-Clause
Author: Can H. Tartanoglu
Author-email: canhtart@gmail.com
Maintainer: Can H. Tartanoglu
Maintainer-email: canhtart@gmail.com
Requires-Python: >=3.12,<4.0
Classifier: Development Status :: 4 - Beta
Classifier: License :: OSI Approved :: BSD License
Classifier: Operating System :: OS Independent
Classifier: Programming Language :: Python :: 3
Classifier: Programming Language :: Python :: 3.12
Classifier: Programming Language :: Python :: 3.13
Provides-Extra: gen
Requires-Dist: Wikipedia-API (>=0.5.4,<0.6.0) ; extra == "gen"
Requires-Dist: deepdiff (>=7.0.1,<8.0.0) ; extra == "gen"
Requires-Dist: pandas[compression,excel,parquet] ; extra == "gen"
Requires-Dist: pydantic (>=2,<3)
Project-URL: Repository, https://github.com/memorycircuits/neurometa
